[
    {
        "Title": "2015 prend la Porte - Le calendrier de l'avent du 16 au 31 juillet 2015",
        "Link to sample": "https://samples.audible.com/bk/adfr/000332/bk_adfr_000332_sample.mp3",
        "By": "DidierPorte",
        "Narrated by": "MarcToupence",
        "Series": "QuoideMeuf,Book3",
        "Length": "6mins",
        "Release date": "12-14-15",
        "Language": "French",
        "Ratings": "5outof51rating"
    },
    {
        "Title": "2015 prend la Porte - Le calendrier de l'avent du 16 au 31 mai 2015",
        "Link to sample": "https://samples.audible.com/bk/adfr/000328/bk_adfr_000328_sample.mp3",
        "By": "DidierPorte",
        "Narrated by": "DidierPorte",
        "Series": "ComedyNewsWeekly-Saison2,Book9",
        "Length": "6mins",
        "Release date": "12-10-15",
        "Language": "French",
        "Ratings": "5outof51rating"
    },
    {
        "Title": "2015 prend la Porte - Le calendrier de l'avent du 16 au 31 octobre 2015",
        "Link to sample": "https://samples.audible.com/bk/adfr/000338/bk_adfr_000338_sample.mp3",
        "By": "DidierPorte",
        "Narrated by": "DidierPorte",
        "Series": "Proverbes",
        "Length": "6mins",
        "Release date": "12-20-15",
        "Language": "French",
        "Ratings": "5outof51rating"
    },
    {
        "Title": "2015 prend la Porte - Le calendrier de l'avent du 1er au 12 décembre 2015",
        "Link to sample": "https://samples.audible.com/bk/adfr/000341/bk_adfr_000341_sample.mp3",
        "By": "DidierPorte",
        "Narrated by": "DidierPorte",
        "Series": "None",
        "Length": "8mins",
        "Release date": "12-23-15",
        "Language": "French",
        "Ratings": "5outof51rating"
    },
    {
        "Title": "2015 prend la Porte - Le calendrier de l'avent du 1er au 12 novembre 2015",
        "Link to sample": "https://samples.audible.com/bk/adfr/000339/bk_adfr_000339_sample.mp3",
        "By": "DidierPorte",
        "Narrated by": "DidierPorte",
        "Series": "None",
        "Length": "5mins",
        "Release date": "12-21-15",
        "Language": "French",
        "Ratings": "5outof51rating"
    },
    {
        "Title": "2015 prend la Porte - Le calendrier de l'avent du 1er au 14 février 2015",
        "Link to sample": "https://samples.audible.com/bk/adfr/000321/bk_adfr_000321_sample.mp3",
        "By": "DidierPorte",
        "Narrated by": "DidierPorte",
        "Series": "None",
        "Length": "5mins",
        "Release date": "12-03-15",
        "Language": "French",
        "Ratings": "5outof51rating"
    },
    {
        "Title": "2015 prend la Porte - Le calendrier de l'avent du 1er au 15 août 2015",
        "Link to sample": "https://samples.audible.com/bk/adfr/000333/bk_adfr_000333_sample.mp3",
        "By": "DidierPorte",
        "Narrated by": "DidierPorte",
        "Series": "None",
        "Length": "7mins",
        "Release date": "12-15-15",
        "Language": "French",
        "Ratings": "Notratedyet"
    },
    {
        "Title": "2015 prend la Porte - Le calendrier de l'avent du 1er au 15 avril 2015",
        "Link to sample": "https://samples.audible.com/bk/adfr/000325/bk_adfr_000325_sample.mp3",
        "By": "DidierPorte",
        "Narrated by": "DidierPorte",
        "Series": "None",
        "Length": "5mins",
        "Release date": "12-07-15",
        "Language": "French",
        "Ratings": "Notratedyet"
    },
    {
        "Title": "2015 prend la Porte - Le calendrier de l'avent du 1er au 15 janvier 2015",
        "Link to sample": "https://samples.audible.com/bk/adfr/000319/bk_adfr_000319_sample.mp3",
        "By": "DidierPorte",
        "Narrated by": "DidierPorte",
        "Series": "None",
        "Length": "5mins",
        "Release date": "12-01-15",
        "Language": "French",
        "Ratings": "5outof51rating"
    },
    {
        "Title": "2015 prend la Porte - Le calendrier de l'avent du 1er au 15 juillet 2015",
        "Link to sample": "https://samples.audible.com/bk/adfr/000331/bk_adfr_000331_sample.mp3",
        "By": "DidierPorte",
        "Narrated by": "DidierPorte",
        "Series": "None",
        "Length": "6mins",
        "Release date": "12-13-15",
        "Language": "French",
        "Ratings": "5outof51rating"
    },
    {
        "Title": "2015 prend la Porte - Le calendrier de l'avent du 1er au 15 juin 2015",
        "Link to sample": "https://samples.audible.com/bk/adfr/000329/bk_adfr_000329_sample.mp3",
        "By": "DidierPorte",
        "Narrated by": "DidierPorte",
        "Series": "None",
        "Length": "6mins",
        "Release date": "12-11-15",
        "Language": "French",
        "Ratings": "5outof51rating"
    },
    {
        "Title": "2015 prend la Porte - Le calendrier de l'avent du 1er au 15 mai 2015",
        "Link to sample": "https://samples.audible.com/bk/adfr/000327/bk_adfr_000327_sample.mp3",
        "By": "DidierPorte",
        "Narrated by": "DidierPorte",
        "Series": "None",
        "Length": "5mins",
        "Release date": "12-09-15",
        "Language": "French",
        "Ratings": "5outof51rating"
    },
    {
        "Title": "2015 prend la Porte - Le calendrier de l'avent du 1er au 15 mars 2015",
        "Link to sample": "https://samples.audible.com/bk/adfr/000323/bk_adfr_000323_sample.mp3",
        "By": "DidierPorte",
        "Narrated by": "DidierPorte",
        "Series": "None",
        "Length": "5mins",
        "Release date": "12-05-15",
        "Language": "French",
        "Ratings": "5outof51rating"
    },
    {
        "Title": "2015 prend la Porte - Le calendrier de l'avent du 1er au 15 octobre 2015",
        "Link to sample": "https://samples.audible.com/bk/adfr/000337/bk_adfr_000337_sample.mp3",
        "By": "DidierPorte",
        "Narrated by": "DidierPorte",
        "Series": "None",
        "Length": "7mins",
        "Release date": "12-19-15",
        "Language": "French",
        "Ratings": "5outof51rating"
    },
    {
        "Title": "2015 prend la Porte - Le calendrier de l'avent du 1er au 15 septembre 2015",
        "Link to sample": "https://samples.audible.com/bk/adfr/000335/bk_adfr_000335_sample.mp3",
        "By": "DidierPorte",
        "Narrated by": "DidierPorte",
        "Series": "None",
        "Length": "5mins",
        "Release date": "12-17-15",
        "Language": "French",
        "Ratings": "5outof51rating"
    },
    {
        "Title": "2015 prend la Porte. Le calendrier de l'avent du 16 au 31 mars 2015",
        "Link to sample": "https://samples.audible.com/bk/adfr/000324/bk_adfr_000324_sample.mp3",
        "By": "DidierPorte",
        "Narrated by": "DidierPorte",
        "Series": "None",
        "Length": "5mins",
        "Release date": "12-06-15",
        "Language": "French",
        "Ratings": "5outof51rating"
    },
    {
        "Title": "2017. Féminisme mot de l'année",
        "Link to sample": "https://samples.audible.com/bk/nefr/000060/bk_nefr_000060_sample.mp3",
        "By": "MélanieWanga,ClémentineGallot",
        "Narrated by": "DidierPorte",
        "Series": "None",
        "Length": "59mins",
        "Release date": "01-12-18",
        "Language": "French",
        "Ratings": "Notratedyet"
    },
    {
        "Title": "2031, Travailler au temps de l'IA",
        "Link to sample": "https://samples.audible.com/bk/edel/022797/bk_edel_022797_sample.mp3",
        "By": "ChristopheVictor",
        "Narrated by": "MélanieWanga,ClémentineGallot,JulietteReitzer,Kiyémis",
        "Series": "None",
        "Length": "5hrsand1min",
        "Release date": "02-15-21",
        "Language": "French",
        "Ratings": "Notratedyet"
    },
    {
        "Title": "2034",
        "Link to sample": "https://samples.audible.com/bk/adfr/002571/bk_adfr_002571_sample.mp3",
        "By": "HugoLisoir,MaximeLisoir",
        "Narrated by": "SethShannon",
        "Series": "None",
        "Length": "5hrsand24mins",
        "Release date": "06-30-21",
        "Language": "French",
        "Ratings": "Notratedyet"
    },
    {
        "Title": "2040 : Tous dans l'espace",
        "Link to sample": "https://samples.audible.com/bk/adfr/001566/bk_adfr_001566_sample.mp3",
        "By": "ArthurC.Clarke",
        "Narrated by": "ThierryBlanc",
        "Series": "None",
        "Length": "7hrsand3mins",
        "Release date": "11-14-19",
        "Language": "French",
        "Ratings": "Notratedyet"
    },
    {
        "Title": "2061. L'Odyssée trois",
        "Link to sample": "https://samples.audible.com/bk/gall/000162/bk_gall_000162_sample.mp3",
        "By": "BoualemSansal",
        "Narrated by": "MatthieuDahan",
        "Series": "None",
        "Length": "7hrsand56mins",
        "Release date": "01-15-16",
        "Language": "French",
        "Ratings": "3outof51rating"
    },
    {
        "Title": "2084. La fin du monde",
        "Link to sample": "https://samples.audible.com/bk/cids/000430/bk_cids_000430_sample.mp3",
        "By": "HansChristianAndersen",
        "Narrated by": "ThierryHancisse,PierreHancisse",
        "Series": "None",
        "Length": "4hrsand28mins",
        "Release date": "01-13-15",
        "Language": "French",
        "Ratings": "4outof58ratings"
    },
    {
        "Title": "20th Century Toys",
        "Link to sample": "https://samples.audible.com/bk/acx0/207656/bk_acx0_207656_sample.mp3",
        "By": "JulieCorbeil",
        "Narrated by": "FabienneProst",
        "Series": "None",
        "Length": "9mins",
        "Release date": "07-28-20",
        "Language": "French",
        "Ratings": "Notratedyet"
    },
    {
        "Title": "21 contes rares",
        "Link to sample": "https://samples.audible.com/bk/fabp/000510/bk_fabp_000510_sample.mp3",
        "By": "BrianTracy",
        "Narrated by": "NancyKeli",
        "Series": "None",
        "Length": "2hrsand50mins",
        "Release date": "09-14-18",
        "Language": "French",
        "Ratings": "Notratedyet"
    },
    {
        "Title": "ET Si... Je Vivais Dans La Gratitude? [What If...I Live in Graditude]",
        "Link to sample": "https://samples.audible.com/bk/piva/000001/bk_piva_000001_sample.mp3",
        "By": "PierreVancoillié",
        "Narrated by": "BertrandMaudet",
        "Series": "None",
        "Length": "3hrsand16mins",
        "Release date": "02-26-21",
        "Language": "French",
        "Ratings": "Notratedyet"
    },
    {
        "Title": "Avalez le crapaud",
        "Link to sample": "https://samples.audible.com/bk/cofr/000291/bk_cofr_000291_sample.mp3",
        "By": "WillBowen",
        "Narrated by": "PierreVancoillié",
        "Series": "None",
        "Length": "4hrsand30mins",
        "Release date": "01-17-18",
        "Language": "French",
        "Ratings": "5outof58ratings"
    },
    {
        "Title": "21 jours de travail pour une rente à vie",
        "Link to sample": "https://samples.audible.com/bk/odlb/002085/bk_odlb_002085_sample.mp3",
        "By": "YuvalNoahHarari",
        "Narrated by": "AlexandreStanké",
        "Series": "None",
        "Length": "11hrsand52mins",
        "Release date": "11-28-18",
        "Language": "French",
        "Ratings": "Notratedyet"
    },
    {
        "Title": "21 jours sans se plaindre. Changez d'habitude, changez votre vie, changez le monde",
        "Link to sample": "https://samples.audible.com/sp/adaa/000132/sp_adaa_000132_sample.mp3",
        "By": "MarianneWilliamson",
        "Narrated by": "PhilippeSollier",
        "Series": "None",
        "Length": "3hrsand55mins",
        "Release date": "02-07-14",
        "Language": "French",
        "Ratings": "Notratedyet"
    },
    {
        "Title": "21 leçons pour le XXIe siècle",
        "Link to sample": "https://samples.audible.com/bk/lizz/000709/bk_lizz_000709_sample.mp3",
        "By": "HarvardBusinessReview",
        "Narrated by": "DanièlePanneton",
        "Series": "None",
        "Length": "7hrsand33mins",
        "Release date": "06-10-21",
        "Language": "French",
        "Ratings": "4.5outof526ratings"
    },
    {
        "Title": "Un cours pour maigrir",
        "Link to sample": "https://samples.audible.com/bk/gagn/000056/bk_gagn_000056_sample.mp3",
        "By": "ThierryNadisic",
        "Narrated by": "FrançoisHatt",
        "Series": "None",
        "Length": "5hrs",
        "Release date": "08-26-21",
        "Language": "French",
        "Ratings": "4outof53ratings"
    },
    {
        "Title": "21 Millions - Capital",
        "Link to sample": "https://samples.audible.com/bk/odlb/000272/bk_odlb_000272_sample.mp3",
        "By": "DanGagnon",
        "Narrated by": "HervéCarrasco",
        "Series": "None",
        "Length": "1hrand1min",
        "Release date": "10-16-17",
        "Language": "French",
        "Ratings": "Notratedyet"
    },
    {
        "Title": "Conjuguez performance et bien-être",
        "Link to sample": "https://samples.audible.com/bk/cids/000801/bk_cids_000801_sample.mp3",
        "By": "StephenKing",
        "Narrated by": "AnthonyMirelli",
        "Series": "None",
        "Length": "36hrsand5mins",
        "Release date": "06-04-13",
        "Language": "French",
        "Ratings": "Notratedyet"
    },
    {
        "Title": "S'épanouir en temps de crise",
        "Link to sample": "https://samples.audible.com/bk/cids/000453/bk_cids_000453_sample.mp3",
        "By": "auteurinconnu",
        "Narrated by": "FrançoisMontagut",
        "Series": "None",
        "Length": "53mins",
        "Release date": "08-17-17",
        "Language": "French",
        "Ratings": "Notratedyet"
    },
    {
        "Title": "22 bonnes raisons d'écouter cet épisode. La 21e va vous étonner",
        "Link to sample": "https://samples.audible.com/bk/adfo/000258/bk_adfo_000258_sample.mp3",
        "By": "CharlesPerrault,FrèresGrimm,HansChristianAndersen",
        "Narrated by": "NicolasPlanchais",
        "Series": "None",
        "Length": "2hrsand3mins",
        "Release date": "10-27-15",
        "Language": "French",
        "Ratings": "5outof51rating"
    },
    {
        "Title": "22/11/63 [French Version]",
        "Link to sample": "https://samples.audible.com/bk/erbj/000001/bk_erbj_000001_sample.mp3",
        "By": "PhilipMatyszak",
        "Narrated by": "Diversnarrateurs",
        "Series": "None",
        "Length": "7hrsand46mins",
        "Release date": "12-04-20",
        "Language": "French",
        "Ratings": "3.5outof533ratings"
    },
    {
        "Title": "230 proverbes chinois",
        "Link to sample": "https://samples.audible.com/bk/acx0/125561/bk_acx0_125561_sample.mp3",
        "By": "ErikBjork",
        "Narrated by": "MathieuBuscatto",
        "Series": "None",
        "Length": "5hrsand2mins",
        "Release date": "11-25-15",
        "Language": "French",
        "Ratings": "Notratedyet"
    },
    {
        "Title": "24 contes et chansons pour les petits enfants !",
        "Link to sample": "https://samples.audible.com/bk/cids/000455/bk_cids_000455_sample.mp3",
        "By": "ManoelJunior",
        "Narrated by": "ErikBjork,AnouckMontreuil",
        "Series": "None",
        "Length": "16hrsand47mins",
        "Release date": "08-27-18",
        "Language": "French",
        "Ratings": "Notratedyet"
    },
    {
        "Title": "24 heures dans la Rome Antique",
        "Link to sample": "https://samples.audible.com/bk/jaco/000002/bk_jaco_000002_sample.mp3",
        "By": "CharlesPerrault,FrèresGrimm,HansChristianAndersen",
        "Narrated by": "Jeann-BernardHiran,ElissaMleiel",
        "Series": "None",
        "Length": "2hrsand52mins",
        "Release date": "10-27-15",
        "Language": "French",
        "Ratings": "Notratedyet"
    },
    {
        "Title": "24 histoires d'AVENT Noël",
        "Link to sample": "https://samples.audible.com/bk/pjca/000506/bk_pjca_000506_sample.mp3",
        "By": "ChristopheAndré",
        "Narrated by": "Diversnarrateurs",
        "Series": "None",
        "Length": "2hrsand25mins",
        "Release date": "02-04-20",
        "Language": "French",
        "Ratings": "Notratedyet"
    },
    {
        "Title": "24FPS",
        "Link to sample": "https://samples.audible.com/bk/vuvo/000051/bk_vuvo_000051_sample.mp3",
        "By": "JacquesPrévert",
        "Narrated by": "ChristopheAndré",
        "Series": "None",
        "Length": "36mins",
        "Release date": "02-24-20",
        "Language": "French",
        "Ratings": "Notratedyet"
    },
    {
        "Title": "24H Pujadas - Les partis pris",
        "Link to sample": "https://samples.audible.com/bk/acx0/255774/bk_acx0_255774_sample.mp3",
        "By": "VanessaBeaulieu",
        "Narrated by": "CatherineArditi,RichardBohringer,Jean-ClaudeBrialy,BrigitteFossey,AnnieGirardot,JeanGuidoni",
        "Series": "None",
        "Length": "5hrsand39mins",
        "Release date": "12-20-18",
        "Language": "French",
        "Ratings": "Notratedyet"
    },
    {
        "Title": "25 Ans de Solitude [25 Years of Solitude]",
        "Link to sample": "https://samples.audible.com/sp/cids/000360/sp_cids_000360_sample.mp3",
        "By": "JCArmand",
        "Narrated by": "MylèneSt-Sauveur",
        "Series": "None",
        "Length": "54mins",
        "Release date": "05-05-21",
        "Language": "French",
        "Ratings": "Notratedyet"
    },
    {
        "Title": "25 contes et chansons pour les filles",
        "Link to sample": "https://samples.audible.com/bk/adfo/000232/bk_adfo_000232_sample.mp3",
        "By": "div.",
        "Narrated by": "NatalieChantalMarie",
        "Series": "None",
        "Length": "48mins",
        "Release date": "11-17-14",
        "Language": "French",
        "Ratings": "5outof51rating"
    },
    {
        "Title": "Sérénité",
        "Link to sample": "None",
        "By": "OliverWunderlich",
        "Narrated by": "JeanVilar",
        "Series": "None",
        "Length": "28mins",
        "Release date": "10-26-20",
        "Language": "French",
        "Ratings": "5outof51rating"
    },
    {
        "Title": "Jacques Prévert",
        "Link to sample": "None",
        "By": "None",
        "Narrated by": "MarcToupence",
        "Series": "None",
        "Length": "None",
        "Release date": "None",
        "Language": "None",
        "Ratings": "5outof51rating"
    },
    {
        "Title": "Mes tempêtes intérieurs [My Inner Storms]",
        "Link to sample": "None",
        "By": "None",
        "Narrated by": "None",
        "Series": "None",
        "Length": "None",
        "Release date": "None",
        "Language": "None",
        "Ratings": "5outof51rating"
    },
    {
        "Title": "French for Children",
        "Link to sample": "None",
        "By": "None",
        "Narrated by": "None",
        "Series": "None",
        "Length": "None",
        "Release date": "None",
        "Language": "None",
        "Ratings": "Notratedyet"
    },
    {
        "Title": "28 Lettres : l'arabe en podcast",
        "Link to sample": "None",
        "By": "None",
        "Narrated by": "None",
        "Series": "None",
        "Length": "None",
        "Release date": "None",
        "Language": "None",
        "Ratings": "Notratedyet"
    },
    {
        "Title": "28 poèmes de Charles d'Orléans à Apollinaire",
        "Link to sample": "None",
        "By": "None",
        "Narrated by": "None",
        "Series": "None",
        "Length": "None",
        "Release date": "None",
        "Language": "None",
        "Ratings": "4outof51rating"
    },
    {
        "Title": "Deep Sleep. Le Pilote",
        "Link to sample": "None",
        "By": "None",
        "Narrated by": "None",
        "Series": "None",
        "Length": "None",
        "Release date": "None",
        "Language": "None",
        "Ratings": "Notratedyet"
    }
]