[
    {
        "Title": "La série \"Sex Education\" de Laurie Nunn",
        "Link to sample": "https://samples.audible.com/bk/nefr/000895/bk_nefr_000895_sample.mp3",
        "By": "ClémentineGallot,Anne-LaurePineau",
        "Narrated by": "NicholasSavard-L'Herbier,ElianePréfontaine",
        "Series": "QuoideMeuf,Book31",
        "Length": "17mins",
        "Release date": "05-07-19",
        "Language": "French",
        "Ratings": "Notratedyet"
    },
    {
        "Title": "La fée flocon",
        "Link to sample": "https://samples.audible.com/bk/edgl/000024/bk_edgl_000024_sample.mp3",
        "By": "MarlèneJobert",
        "Narrated by": "ClémentineGallot,Anne-LaurePineau",
        "Series": "MarlèneJobertraconte",
        "Length": "17mins",
        "Release date": "02-27-18",
        "Language": "French",
        "Ratings": "Notratedyet"
    },
    {
        "Title": "Poésie. Gérard de Nerval",
        "Link to sample": "https://samples.audible.com/bk/cids/000874/bk_cids_000874_sample.mp3",
        "By": "GérarddeNerval",
        "Narrated by": "MarlèneJobert",
        "Series": "Poésie",
        "Length": "17mins",
        "Release date": "12-06-17",
        "Language": "French",
        "Ratings": "Notratedyet"
    },
    {
        "Title": "100 citations de Cicéron",
        "Link to sample": "https://samples.audible.com/bk/cids/000663/bk_cids_000663_sample.mp3",
        "By": "Cicéron",
        "Narrated by": "JeanVilar",
        "Series": "Les100citationsde...",
        "Length": "17mins",
        "Release date": "05-20-16",
        "Language": "French",
        "Ratings": "Notratedyet"
    },
    {
        "Title": "Le viral existe-t-il encore en 2017 ?",
        "Link to sample": "https://samples.audible.com/bk/vlan/000001/bk_vlan_000001_sample.mp3",
        "By": "GrégoryPouy",
        "Narrated by": "ÉlodieHuber",
        "Series": "Vlan,Book1",
        "Length": "17mins",
        "Release date": "12-12-17",
        "Language": "French",
        "Ratings": "3outof52ratings"
    },
    {
        "Title": "Un frère en bocal",
        "Link to sample": "https://samples.audible.com/bk/bjma/000013/bk_bjma_000013_sample.mp3",
        "By": "ÉmilieChazerand",
        "Narrated by": "GrégoryPouy,GeorgesMohammedCherif",
        "Series": "Changemavie,Book181",
        "Length": "17mins",
        "Release date": "08-24-17",
        "Language": "French",
        "Ratings": "Notratedyet"
    },
    {
        "Title": "Une nuit bizarre, bizarre",
        "Link to sample": "https://samples.audible.com/bk/edgl/000528/bk_edgl_000528_sample.mp3",
        "By": "MarlèneJobert",
        "Narrated by": "AymericDupuy",
        "Series": "Changemavie,Book171",
        "Length": "17mins",
        "Release date": "05-17-21",
        "Language": "French",
        "Ratings": "Notratedyet"
    },
    {
        "Title": "Le Parcours de l'héroïne",
        "Link to sample": "https://samples.audible.com/bk/chma/000674/bk_chma_000674_sample.mp3",
        "By": "ClotildeDusoulier",
        "Narrated by": "MarlèneJobert",
        "Series": "Sesentirbien(151-200),Book154",
        "Length": "17mins",
        "Release date": "02-11-21",
        "Language": "French",
        "Ratings": "Notratedyet"
    },
    {
        "Title": "Ceci n’est pas un problème à résoudre",
        "Link to sample": "https://samples.audible.com/bk/chma/000664/bk_chma_000664_sample.mp3",
        "By": "ClotildeDusoulier",
        "Narrated by": "ClotildeDusoulier",
        "Series": "Sesentirbien(101-150),Book150",
        "Length": "17mins",
        "Release date": "11-25-20",
        "Language": "French",
        "Ratings": "Notratedyet"
    },
    {
        "Title": "L'impossible possible",
        "Link to sample": "https://samples.audible.com/bk/sent/000156/bk_sent_000156_sample.mp3",
        "By": "EstherTaillifet",
        "Narrated by": "ClotildeDusoulier",
        "Series": "QuoideMeuf,Book22",
        "Length": "17mins",
        "Release date": "08-26-20",
        "Language": "French",
        "Ratings": "Notratedyet"
    },
    {
        "Title": "L'erreur fondamentale d'attribution",
        "Link to sample": "https://samples.audible.com/bk/sent/000152/bk_sent_000152_sample.mp3",
        "By": "EstherTaillifet",
        "Narrated by": "EstherTaillifet",
        "Series": "Poésie",
        "Length": "17mins",
        "Release date": "07-31-20",
        "Language": "French",
        "Ratings": "Notratedyet"
    },
    {
        "Title": "\"Bonhomme\" de Laurent Sciamma",
        "Link to sample": "https://samples.audible.com/bk/nefr/000886/bk_nefr_000886_sample.mp3",
        "By": "ClémentineGallot,JulieHamaïde",
        "Narrated by": "EstherTaillifet",
        "Series": "Les100citationsde...",
        "Length": "17mins",
        "Release date": "05-07-19",
        "Language": "French",
        "Ratings": "Notratedyet"
    },
    {
        "Title": "Poésie. Charles Baudelaire",
        "Link to sample": "https://samples.audible.com/bk/cids/000876/bk_cids_000876_sample.mp3",
        "By": "CharlesBaudelaire",
        "Narrated by": "ClémentineGallot,JulieHamaïde",
        "Series": "LeNouveauTestament-LaBible,Book17",
        "Length": "17mins",
        "Release date": "12-11-17",
        "Language": "French",
        "Ratings": "Notratedyet"
    },
    {
        "Title": "100 citations de Napoléon Bonaparte",
        "Link to sample": "https://samples.audible.com/bk/cids/000667/bk_cids_000667_sample.mp3",
        "By": "NapoléonBonaparte",
        "Narrated by": "JeanDesailly",
        "Series": "LeNouveauTestament-LaBible,Book11",
        "Length": "17mins",
        "Release date": "05-20-16",
        "Language": "French",
        "Ratings": "5outof51rating"
    },
    {
        "Title": "Petit-Jean des Villes et Sophie Canétang",
        "Link to sample": "https://samples.audible.com/bk/erbj/000004/bk_erbj_000004_sample.mp3",
        "By": "BeatrixPotter",
        "Narrated by": "ÉlodieHuber",
        "Series": "LeNouveauTestament-LaBible,Book10",
        "Length": "17mins",
        "Release date": "12-04-15",
        "Language": "French",
        "Ratings": "Notratedyet"
    },
    {
        "Title": "Tom Pouce",
        "Link to sample": "https://samples.audible.com/bk/acho/000011/bk_acho_000011_sample.mp3",
        "By": "FrèresGrimm",
        "Narrated by": "ErikBjork",
        "Series": "Changemavie(200-250),Book201",
        "Length": "17mins",
        "Release date": "06-06-13",
        "Language": "French",
        "Ratings": "Notratedyet"
    },
    {
        "Title": "Épître de Jacques",
        "Link to sample": "https://samples.audible.com/bk/cids/002335/bk_cids_002335_sample.mp3",
        "By": "auteurinconnu",
        "Narrated by": "AlainCouchot",
        "Series": "CollectionLesLiseuses",
        "Length": "17mins",
        "Release date": "01-10-19",
        "Language": "French",
        "Ratings": "Notratedyet"
    },
    {
        "Title": "Épître aux Colossiens",
        "Link to sample": "https://samples.audible.com/bk/cids/002329/bk_cids_002329_sample.mp3",
        "By": "auteurinconnu",
        "Narrated by": "CyrilDeguillen",
        "Series": "Lesplusbeauxcontespourenfants",
        "Length": "17mins",
        "Release date": "01-10-19",
        "Language": "French",
        "Ratings": "5outof51rating"
    },
    {
        "Title": "Épître aux Philippiens",
        "Link to sample": "https://samples.audible.com/bk/cids/002328/bk_cids_002328_sample.mp3",
        "By": "auteurinconnu",
        "Narrated by": "CyrilDeguillen",
        "Series": "Lesplusbeauxcontespourenfants",
        "Length": "17mins",
        "Release date": "01-10-19",
        "Language": "French",
        "Ratings": "5outof51rating"
    },
    {
        "Title": "Où j'en suis. Vie familiale",
        "Link to sample": "https://samples.audible.com/bk/chma/000694/bk_chma_000694_sample.mp3",
        "By": "ClotildeDusoulier",
        "Narrated by": "CyrilDeguillen",
        "Series": "StandUpPercut",
        "Length": "17mins",
        "Release date": "07-02-21",
        "Language": "French",
        "Ratings": "Notratedyet"
    },
    {
        "Title": "Motivation Interne [Internal Motivation]",
        "Link to sample": "https://samples.audible.com/bk/acx0/264504/bk_acx0_264504_sample.mp3",
        "By": "MentesLibres",
        "Narrated by": "ClotildeDusoulier",
        "Series": "Les100citationsde...",
        "Length": "17mins",
        "Release date": "06-24-21",
        "Language": "French",
        "Ratings": "Notratedyet"
    },
    {
        "Title": "La tâche",
        "Link to sample": "https://samples.audible.com/bk/lizz/000699/bk_lizz_000699_sample.mp3",
        "By": "GaëllePerrin-Guillet",
        "Narrated by": "MentesLibres",
        "Series": "None",
        "Length": "17mins",
        "Release date": "05-12-21",
        "Language": "French",
        "Ratings": "Notratedyet"
    },
    {
        "Title": "Mme Twigadoon [Mrs. Twigadoon]",
        "Link to sample": "https://samples.audible.com/bk/acx0/231663/bk_acx0_231663_sample.mp3",
        "By": "EleanorJoyMcDonald",
        "Narrated by": "JulienChatelet",
        "Series": "None",
        "Length": "17mins",
        "Release date": "01-13-21",
        "Language": "French",
        "Ratings": "Notratedyet"
    },
    {
        "Title": "Mon Zouave",
        "Link to sample": "https://samples.audible.com/bk/lizz/000609/bk_lizz_000609_sample.mp3",
        "By": "TatianadeRosnay",
        "Narrated by": "YasmineMousaid",
        "Series": "None",
        "Length": "17mins",
        "Release date": "01-07-21",
        "Language": "French",
        "Ratings": "Notratedyet"
    },
    {
        "Title": "Odyssée",
        "Link to sample": "https://samples.audible.com/bk/voso/000005/bk_voso_000005_sample.mp3",
        "By": "FrançoisPerrin",
        "Narrated by": "MarionMalenfant",
        "Series": "None",
        "Length": "17mins",
        "Release date": "10-05-20",
        "Language": "French",
        "Ratings": "Notratedyet"
    },
    {
        "Title": "Rois et Sorciers [Kings and Wizards]",
        "Link to sample": "https://samples.audible.com/bk/acx0/194357/bk_acx0_194357_sample.mp3",
        "By": "MorganRice",
        "Narrated by": "SamirBouadi",
        "Series": "None",
        "Length": "17mins",
        "Release date": "04-30-20",
        "Language": "French",
        "Ratings": "Notratedyet"
    },
    {
        "Title": "Comment perdre du poids en bonne santé par la musculation [How to Lose Healthy Weight by Weight Training]",
        "Link to sample": "https://samples.audible.com/bk/acx0/187858/bk_acx0_187858_sample.mp3",
        "By": "CoachKS",
        "Narrated by": "OlivierLovero",
        "Series": "None",
        "Length": "17mins",
        "Release date": "03-25-20",
        "Language": "French",
        "Ratings": "Notratedyet"
    },
    {
        "Title": "Le vilain petit canard",
        "Link to sample": "https://samples.audible.com/bk/fved/000531/bk_fved_000531_sample.mp3",
        "By": "HansChristianAndersen",
        "Narrated by": "ThierryLaflamme",
        "Series": "None",
        "Length": "17mins",
        "Release date": "04-05-19",
        "Language": "French",
        "Ratings": "Notratedyet"
    },
    {
        "Title": "Le vilain petit canard",
        "Link to sample": "https://samples.audible.com/bk/cids/000868/bk_cids_000868_sample.mp3",
        "By": "HansChristianAndersen",
        "Narrated by": "YannickLopez",
        "Series": "None",
        "Length": "17mins",
        "Release date": "12-01-17",
        "Language": "French",
        "Ratings": "Notratedyet"
    },
    {
        "Title": "Hansel et Gretel",
        "Link to sample": "https://samples.audible.com/bk/cids/000856/bk_cids_000856_sample.mp3",
        "By": "FrèresGrimm",
        "Narrated by": "FabienneProst",
        "Series": "None",
        "Length": "17mins",
        "Release date": "12-01-17",
        "Language": "French",
        "Ratings": "Notratedyet"
    },
    {
        "Title": "Papy Superflash",
        "Link to sample": "https://samples.audible.com/bk/bjma/000023/bk_bjma_000023_sample.mp3",
        "By": "BenoîtBroyart",
        "Narrated by": "FabienneProst",
        "Series": "None",
        "Length": "17mins",
        "Release date": "08-23-17",
        "Language": "French",
        "Ratings": "Notratedyet"
    },
    {
        "Title": "Stand UpPercut - Alexis Cabarez",
        "Link to sample": "https://samples.audible.com/bk/kocb/000011/bk_kocb_000011_sample.mp3",
        "By": "AlexisCabarez",
        "Narrated by": "BenoîtBroyart",
        "Series": "None",
        "Length": "17mins",
        "Release date": "04-25-17",
        "Language": "French",
        "Ratings": "Notratedyet"
    },
    {
        "Title": "100 citations de Confucius",
        "Link to sample": "https://samples.audible.com/bk/cids/000664/bk_cids_000664_sample.mp3",
        "By": "Confucius",
        "Narrated by": "AlexisCabarez",
        "Series": "None",
        "Length": "17mins",
        "Release date": "05-20-16",
        "Language": "French",
        "Ratings": "Notratedyet"
    },
    {
        "Title": "Apple Crumble [French Version]",
        "Link to sample": "https://samples.audible.com/bk/lhar/000009/bk_lhar_000009_sample.mp3",
        "By": "CamilleBrunel",
        "Narrated by": "ÉlodieHuber",
        "Series": "None",
        "Length": "17mins",
        "Release date": "10-14-15",
        "Language": "French",
        "Ratings": "Notratedyet"
    },
    {
        "Title": "Les cadeaux inutiles",
        "Link to sample": "https://samples.audible.com/bk/cara/000029/bk_cara_000029_sample.mp3",
        "By": "O.Henry",
        "Narrated by": "CamilleBrunel",
        "Series": "None",
        "Length": "17mins",
        "Release date": "05-19-11",
        "Language": "French",
        "Ratings": "Notratedyet"
    },
    {
        "Title": "Ephésiens - version Segond 21",
        "Link to sample": "https://samples.audible.com/bk/sbdg/000059/bk_sbdg_000059_sample.mp3",
        "By": "Paul",
        "Narrated by": "FabienneProst",
        "Series": "None",
        "Length": "17mins",
        "Release date": "02-21-13",
        "Language": "French",
        "Ratings": "Notratedyet"
    },
    {
        "Title": "Galates - version Segond 21",
        "Link to sample": "https://samples.audible.com/bk/sbdg/000058/bk_sbdg_000058_sample.mp3",
        "By": "Paul",
        "Narrated by": "Jean-MicaëlSaltzmann",
        "Series": "None",
        "Length": "17mins",
        "Release date": "02-25-13",
        "Language": "French",
        "Ratings": "Notratedyet"
    },
    {
        "Title": "Peau d'âne",
        "Link to sample": "https://samples.audible.com/pf/cids/000220/pf_cids_000220_sample.mp3",
        "By": "CharlesPerrault",
        "Narrated by": "Jean-MicaëlSaltzmann",
        "Series": "None",
        "Length": "17mins",
        "Release date": "03-21-11",
        "Language": "French",
        "Ratings": "Notratedyet"
    },
    {
        "Title": "Histoire du caoutchouc - conte pour enfants",
        "Link to sample": "https://samples.audible.com/bk/cids/000274/bk_cids_000274_sample.mp3",
        "By": "PaulTripp",
        "Narrated by": "PierreDelbon,EdithLoria",
        "Series": "None",
        "Length": "17mins",
        "Release date": "02-20-13",
        "Language": "French",
        "Ratings": "Notratedyet"
    },
    {
        "Title": "Cantique des cantiques - version Segond 21",
        "Link to sample": "https://samples.audible.com/bk/sbdg/000032/bk_sbdg_000032_sample.mp3",
        "By": "Salomon",
        "Narrated by": "RobertManuel",
        "Series": "None",
        "Length": "17mins",
        "Release date": "02-21-13",
        "Language": "French",
        "Ratings": "Notratedyet"
    },
    {
        "Title": "Les aventures d'un zoo",
        "Link to sample": "https://samples.audible.com/bk/cids/000272/bk_cids_000272_sample.mp3",
        "By": "PaulTripp",
        "Narrated by": "Jean-MicaëlSaltzmann",
        "Series": "None",
        "Length": "17mins",
        "Release date": "02-20-13",
        "Language": "French",
        "Ratings": "Notratedyet"
    },
    {
        "Title": "Hansel et Gretel",
        "Link to sample": "https://samples.audible.com/bk/cids/000141/bk_cids_000141_sample.mp3",
        "By": "FrèresGrimm",
        "Narrated by": "RobertManuel",
        "Series": "None",
        "Length": "17mins",
        "Release date": "02-16-10",
        "Language": "French",
        "Ratings": "Notratedyet"
    },
    {
        "Title": "L'Enfant d'Eléphant",
        "Link to sample": "https://samples.audible.com/bk/cara/000004/bk_cara_000004_sample.mp3",
        "By": "RudyardKipling",
        "Narrated by": "CélineLucas",
        "Series": "None",
        "Length": "17mins",
        "Release date": "06-09-09",
        "Language": "French",
        "Ratings": "Notratedyet"
    },
    {
        "Title": "Guerre froide",
        "Link to sample": "https://samples.audible.com/bk/odlb/000352/bk_odlb_000352_sample.mp3",
        "By": "DouglasKennedy",
        "Narrated by": "FabienneProst",
        "Series": "None",
        "Length": "17mins",
        "Release date": "07-03-14",
        "Language": "French",
        "Ratings": "Notratedyet"
    },
    {
        "Title": "Maman Abricot",
        "Link to sample": "https://samples.audible.com/bk/brut/000013/bk_brut_000013_sample.mp3",
        "By": "StéphaneChamak",
        "Narrated by": "XavierPercy",
        "Series": "None",
        "Length": "17mins",
        "Release date": "12-20-13",
        "Language": "French",
        "Ratings": "Notratedyet"
    },
    {
        "Title": "Letiko, la fille du Soleil",
        "Link to sample": "https://samples.audible.com/bk/bjma/000006/bk_bjma_000006_sample.mp3",
        "By": "NataCaputo",
        "Narrated by": "MartialLeminoux,MaxJoseph",
        "Series": "None",
        "Length": "17mins",
        "Release date": "02-02-15",
        "Language": "French",
        "Ratings": "Notratedyet"
    },
    {
        "Title": "12 comptines rares à découvrir",
        "Link to sample": "https://samples.audible.com/pf/cids/000422/pf_cids_000422_sample.mp3",
        "By": "AnneChristine",
        "Narrated by": "MarylineFontaine,RobertLucibello,IsabelleDangerfield,BernadetteLacombe",
        "Series": "None",
        "Length": "17mins",
        "Release date": "01-13-15",
        "Language": "French",
        "Ratings": "Notratedyet"
    },
    {
        "Title": "Un guide pour débutants Masturbation Femmes [French Edition]",
        "Link to sample": "https://samples.audible.com/bk/acx0/021544/bk_acx0_021544_sample.mp3",
        "By": "JacquelineDonne",
        "Narrated by": "diversnarrateurs",
        "Series": "None",
        "Length": "17mins",
        "Release date": "08-07-14",
        "Language": "French",
        "Ratings": "Notratedyet"
    },
    {
        "Title": "Les Cadeaux inutiles",
        "Link to sample": "https://samples.audible.com/bk/lind/018170/bk_lind_018170_sample.mp3",
        "By": "WilliamO.Henry",
        "Narrated by": "ReneNasser",
        "Series": "None",
        "Length": "17mins",
        "Release date": "08-10-20",
        "Language": "French",
        "Ratings": "Notratedyet"
    },
    {
        "Title": "Chiens de rue - épisode 5: l'arme fatale [Street Dogs - Episode 5: The Lethal Weapon]",
        "Link to sample": "https://samples.audible.com/bk/vuvo/000209/bk_vuvo_000209_sample.mp3",
        "By": "LaurentChabin",
        "Narrated by": "FabienneProst",
        "Series": "None",
        "Length": "17mins",
        "Release date": "04-27-20",
        "Language": "French",
        "Ratings": "Notratedyet"
    }
]